[{"pattern":"http:\/\/readms.com\/r\/area_d\/","prefix":"Area_D"},{"pattern":"http:\/\/readms.com\/r\/hsdk\/","prefix":"HSD_Kenichi"},{"pattern":"http:\/\/readms.com\/r\/fairy_tail\/","prefix":"Fairy_Tail"},{"pattern":"http:\/\/readms.com\/r\/bleach\/","prefix":"Bleach"},{"pattern":"http:\/\/readms.com\/r\/naruto\/","prefix":"Naruto"},{"pattern":"http:\/\/readms.com\/r\/one_piece\/","prefix":"One_Piece"},{"pattern":"http:\/\/readms.com\/r\/arslan\/","prefix":"Arslan"},{"pattern":"http:\/\/www.batoto.net\/comic\/_\/comics\/shokugeki-no-soma","prefix":"Shokugeki_no_Soma"},{"pattern":"http:\/\/www.batoto.net\/read\/_\/224290\/onepunch-man","prefix":"OPM"},{"pattern":"http:\/\/readms.com\/r\/rock_lee","prefix":"Rock_Lee"},{"pattern":"http:\/\/readms.com\/r\/attack_on_titan\/","prefix":"Shingeki_no_Kyojin"},{"pattern":"http:\/\/readms.com\/r\/hunter_x_hunter\/","prefix":"HXH"}]